twitchlivechecker/__init__.py
twitchlivechecker/__main__.py
twitchlivechecker/config.py
twitchlivechecker-0.1.0.dist-info/WHEEL
twitchlivechecker-0.1.0.dist-info/METADATA
twitchlivechecker-0.1.0.dist-info/RECORD
