Metadata-Version: 2.1
Name: twitchlivechecker
Version: 0.1.0
Summary: 
Author: n00bady
Author-email: kaz00@vivaldi.net
Requires-Python: >=3.10,<4.0
Classifier: Programming Language :: Python :: 3
Classifier: Programming Language :: Python :: 3.10
Requires-Dist: bs4 (>=0.0.1,<0.0.2)
Requires-Dist: requests (>=2.28.1,<3.0.0)
